{
  "multipart": [
    { "when": { "intake": "south" }, "apply": { "model": "ductwork:block/collector_intake" } },
    { "when": { "intake": "west" },  "apply": { "model": "ductwork:block/collector_intake", "y":  90 } },
    { "when": { "intake": "north" }, "apply": { "model": "ductwork:block/collector_intake", "y": 180 } },
    { "when": { "intake": "east" },  "apply": { "model": "ductwork:block/collector_intake", "y": 270 } },
    { "when": { "intake": "up" },    "apply": { "model": "ductwork:block/collector_intake", "x":  90 } },
    { "when": { "intake": "down" },  "apply": { "model": "ductwork:block/collector_intake", "x": 270 } },

    { "when": { "facing": "north" }, "apply": { "model": "ductwork:block/collector_output" } },
    { "when": { "facing": "east" },  "apply": { "model": "ductwork:block/collector_output", "y":  90 } },
    { "when": { "facing": "south" }, "apply": { "model": "ductwork:block/collector_output", "y": 180 } },
    { "when": { "facing": "west" },  "apply": { "model": "ductwork:block/collector_output", "y": 270 } },
    { "when": { "facing": "down" },  "apply": { "model": "ductwork:block/collector_output", "x":  90 } },
    { "when": { "facing": "up" },    "apply": { "model": "ductwork:block/collector_output", "x": 270 } },

    { "when": { "north": "true" }, "apply": { "model": "ductwork:block/duct_input" } },
    { "when": { "east":  "true" }, "apply": { "model": "ductwork:block/duct_input", "y":  90 } },
    { "when": { "south": "true" }, "apply": { "model": "ductwork:block/duct_input", "y": 180 } },
    { "when": { "west":  "true" }, "apply": { "model": "ductwork:block/duct_input", "y": 270 } },
    { "when": { "down":  "true" }, "apply": { "model": "ductwork:block/duct_input", "x":  90 } },
    { "when": { "up":    "true" }, "apply": { "model": "ductwork:block/duct_input", "x": 270 } }
  ]
}